pixegami/__init__.py
pixegami/main.py
pixegami-0.3.dist-info/METADATA
pixegami-0.3.dist-info/WHEEL
pixegami-0.3.dist-info/entry_points.txt
pixegami-0.3.dist-info/top_level.txt
pixegami-0.3.dist-info/RECORD
