Metadata-Version: 2.1
Name: pixegami
Version: 0.3
Requires-Dist: numpy >=1.11.1
